chewc/__init__.py
chewc/_modidx.py
chewc/core.py
chewc/cross.py
chewc/crossing.py
chewc/meiosis.py
chewc/trait.py
ChewC-0.0.7.dist-info/LICENSE
ChewC-0.0.7.dist-info/METADATA
ChewC-0.0.7.dist-info/WHEEL
ChewC-0.0.7.dist-info/entry_points.txt
ChewC-0.0.7.dist-info/top_level.txt
ChewC-0.0.7.dist-info/RECORD
